airstack/__init__.py
airstack/constant.py
airstack/execute_query.py
airstack/generic.py
airstack/popular_queries.py
airstack/send_request.py
airstack-0.0.7.dist-info/METADATA
airstack-0.0.7.dist-info/WHEEL
airstack-0.0.7.dist-info/top_level.txt
airstack-0.0.7.dist-info/RECORD
